grid_sort/__init__.py
grid_sort/sorting.py
grid_sort-0.1.0.dist-info/licenses/LICENSE
grid_sort-0.1.0.dist-info/METADATA
grid_sort-0.1.0.dist-info/WHEEL
grid_sort-0.1.0.dist-info/top_level.txt
grid_sort-0.1.0.dist-info/RECORD
