Metadata-Version: 2.4
Name: grid-sort
Version: 0.1.0
Summary: A package for sorting 2D points into rows
Home-page: https://github.com/Lrfoster03/Grid-Sort
Author: Lrfoster03
Author-email: lrfoster03@gmail.com
Classifier: Programming Language :: Python :: 3
Classifier: License :: OSI Approved :: MIT License
Classifier: Operating System :: OS Independent
Requires-Python: >=3.6
License-File: LICENSE
Dynamic: author
Dynamic: author-email
Dynamic: classifier
Dynamic: description
Dynamic: description-content-type
Dynamic: home-page
Dynamic: license-file
Dynamic: requires-python
Dynamic: summary
